gaaqoo/__init__.py
gaaqoo/command_line.py
gaaqoo/convert.py
gaaqoo-1.0.1.dist-info/licenses/LICENSE.txt
gaaqoo-1.0.1.dist-info/METADATA
gaaqoo-1.0.1.dist-info/WHEEL
gaaqoo-1.0.1.dist-info/entry_points.txt
gaaqoo-1.0.1.dist-info/top_level.txt
gaaqoo-1.0.1.dist-info/RECORD
