Metadata-Version: 2.4
Name: gaaqoo
Version: 1.0.1
Summary: Convert images into ones suitable for digital photo frames.
Author-email: uraxy <uraxy123@gmail.com>
License: MIT
Project-URL: Homepage, https://github.com/uraxy/gaaqoo
Classifier: Environment :: Console
Classifier: Programming Language :: Python
Classifier: Programming Language :: Python :: 3
Classifier: Programming Language :: Python :: 3.10
Classifier: Programming Language :: Python :: 3.11
Classifier: Programming Language :: Python :: 3.12
Classifier: License :: OSI Approved :: MIT License
Classifier: Topic :: Multimedia :: Graphics :: Graphics Conversion
Classifier: Topic :: Utilities
Requires-Python: >=3.10
License-File: LICENSE.txt
Requires-Dist: Pillow>=10.0.0
Requires-Dist: PyYAML>=6.0
Dynamic: license-file
